taggit_bulk/__init__.py
taggit_bulk/actions.py
taggit_bulk/forms.py
taggit_bulk/settings.py
taggit_bulk/urls.py
taggit_bulk/version.py
taggit_bulk/views.py
taggit_bulk/templates/taggit_bulk/wizard/form.html
django_taggit_bulk-0.0.4b1.dist-info/LICENSE
django_taggit_bulk-0.0.4b1.dist-info/METADATA
django_taggit_bulk-0.0.4b1.dist-info/WHEEL
django_taggit_bulk-0.0.4b1.dist-info/top_level.txt
django_taggit_bulk-0.0.4b1.dist-info/RECORD
